README.md
setup.py
pyspinnaker.egg-info/PKG-INFO
pyspinnaker.egg-info/SOURCES.txt
pyspinnaker.egg-info/dependency_links.txt
pyspinnaker.egg-info/top_level.txt
spinnaker/__init__.py
spinnaker/client.py