Metadata-Version: 2.1
Name: pyspinnaker
Version: 0.0.1
Summary: A python implementation of the Spinnaker API
Home-page: https://github.com/jdewinne/pyspinnaker
Author: Joris De Winne
Author-email: joris.dewinne@gmail.com
License: UNKNOWN
Platform: UNKNOWN
Classifier: Programming Language :: Python :: 3
Classifier: License :: OSI Approved :: MIT License
Classifier: Operating System :: OS Independent
